LICENSE
README.md
setup.py
hs_detection/__init__.py
hs_detection/recording.py
hs_detection/version.py
hs_detection.egg-info/PKG-INFO
hs_detection.egg-info/SOURCES.txt
hs_detection.egg-info/dependency_links.txt
hs_detection.egg-info/not-zip-safe
hs_detection.egg-info/requires.txt
hs_detection.egg-info/top_level.txt
hs_detection/../README.md
hs_detection/detect/Detection.cpp
hs_detection/detect/Detection.h
hs_detection/detect/Detection.pxd
hs_detection/detect/Point.h
hs_detection/detect/ProbeLayout.cpp
hs_detection/detect/ProbeLayout.h
hs_detection/detect/RollingArray.h
hs_detection/detect/Spike.h
hs_detection/detect/SpikeQueue.cpp
hs_detection/detect/SpikeQueue.h
hs_detection/detect/TraceWrapper.h
hs_detection/detect/Types.h
hs_detection/detect/__init__.py
hs_detection/detect/detect.pxd
hs_detection/detect/detect.py
hs_detection/detect/QueueProcessor/FirstElemProcessor.h
hs_detection/detect/QueueProcessor/MaxSpikeFinder.cpp
hs_detection/detect/QueueProcessor/MaxSpikeFinder.h
hs_detection/detect/QueueProcessor/QueueProcessor.h
hs_detection/detect/QueueProcessor/SpikeDecayFilterer.cpp
hs_detection/detect/QueueProcessor/SpikeDecayFilterer.h
hs_detection/detect/QueueProcessor/SpikeFilterer.cpp
hs_detection/detect/QueueProcessor/SpikeFilterer.h
hs_detection/detect/SpikeProcessor/SpikeLocalizer.cpp
hs_detection/detect/SpikeProcessor/SpikeLocalizer.h
hs_detection/detect/SpikeProcessor/SpikeProcessor.h
hs_detection/detect/SpikeProcessor/SpikeShapeWriter.cpp
hs_detection/detect/SpikeProcessor/SpikeShapeWriter.h